{
  "schema_version": "pdf_force_fit_v2.3",
  "entry": "pdf_force_fit_v2",
  "source": {
    "product_file_id": "69fc509c5524e8aefe3008b7",
    "cid": "8199038cb77d4dc3bfe70fe034cd7354",
    "supplier_id": "69f1b877908c95ae5aafdcd0",
    "category_id": "d1690411def72aefc4488d2b",
    "series_id": "a7eb6c9290094e97988f8d9d549ec84a",
    "model_id": "c6b0d53838f94109ba6601f74493b7d8",
    "source_annotation": "69fc509c5524e8aefe3008b7---.svg"
  },
  "classification_records": [
    {
      "product_file_id": "69fc509c5524e8aefe3008b7",
      "region_id": "R001",
      "category_name": "mechanical_dimensions",
      "source": "ai",
      "action": "inserted"
    },
    {
      "product_file_id": "69fc509c5524e8aefe3008b7",
      "region_id": "R002",
      "category_name": "mechanical_dimensions",
      "source": "ai",
      "action": "inserted"
    },
    {
      "product_file_id": "69fc509c5524e8aefe3008b7",
      "region_id": "R003",
      "category_name": "mechanical_dimensions",
      "source": "ai",
      "action": "inserted"
    },
    {
      "product_file_id": "69fc509c5524e8aefe3008b7",
      "region_id": "R004",
      "category_name": "power_connector_pinout",
      "source": "ai",
      "action": "inserted"
    },
    {
      "product_file_id": "69fc509c5524e8aefe3008b7",
      "region_id": "R005",
      "category_name": "mechanical_dimensions",
      "source": "ai",
      "action": "inserted"
    },
    {
      "product_file_id": "69fc509c5524e8aefe3008b7",
      "region_id": "R006",
      "category_name": "feedback_connector_pinout",
      "source": "ai",
      "action": "inserted"
    },
    {
      "product_file_id": "69fc509c5524e8aefe3008b7",
      "region_id": "R007",
      "category_name": "feedback_connector_pinout",
      "source": "ai",
      "action": "inserted"
    },
    {
      "product_file_id": "69fc509c5524e8aefe3008b7",
      "region_id": "R008",
      "category_name": "mechanical_dimensions",
      "source": "ai",
      "action": "inserted"
    },
    {
      "product_file_id": "69fc509c5524e8aefe3008b7",
      "region_id": "R009",
      "category_name": "mechanical_dimensions",
      "source": "ai",
      "action": "inserted"
    },
    {
      "product_file_id": "69fc509c5524e8aefe3008b7",
      "region_id": "R010",
      "category_name": "power_connector_pinout",
      "source": "ai",
      "action": "inserted"
    },
    {
      "product_file_id": "69fc509c5524e8aefe3008b7",
      "region_id": "R011",
      "category_name": "torque_speed_curve",
      "source": "ai",
      "action": "inserted"
    },
    {
      "product_file_id": "69fc509c5524e8aefe3008b7",
      "region_id": "R012",
      "category_name": "torque_speed_curve",
      "source": "ai",
      "action": "inserted"
    },
    {
      "product_file_id": "69fc509c5524e8aefe3008b7",
      "region_id": "R013",
      "category_name": "mechanical_dimensions",
      "source": "ai",
      "action": "inserted"
    },
    {
      "product_file_id": "69fc509c5524e8aefe3008b7",
      "region_id": "R014",
      "category_name": "feedback_connector_pinout",
      "source": "ai",
      "action": "inserted"
    }
  ],
  "regions": [
    {
      "region_id": "R001",
      "group_name": "connector_structure_detail",
      "origin_src": "regions/R001_00ff7f.png",
      "target_src": "regions/R001_00ff7f_trimmed.png",
      "content_type": "structure",
      "is_structure": true,
      "has_gb_standard": false,
      "title": {
        "title_zh": "连接器结构尺寸详图",
        "title_en": "Connector Structure Dimension Detail"
      },
      "classification": {
        "category_name": "mechanical_dimensions",
        "title_zh": "机械尺寸",
        "title_en": "Mechanical Dimensions",
        "category_basis": "用于识别机械结构尺寸类图纸，包括电机/零部件外形轮廓、长宽高、轴径、轴长、键槽、法兰、安装孔、孔距、定位尺寸、三视图、剖视图、局部放大视图、公差、形位公差、基准符号、连接器/线缆/插头的物理安装位置或外形位置。若图中仅展示连接器型号、端子型号、线束走向、接口外形位置，但没有明确的引脚编号、针脚功能、线色或接线表，也归入本类。",
        "reason": "目标裁剪图展示连接器外形结构的侧视图，包含 Housing 型号 'H66L6-02P'、Terminal 型号 'T66L6-B'、插头型号 'SP2111/P5' 和 'SC-06'，以及轴的外形尺寸如 '070h7(-0.03)'、'019h6(-0.013)'、键槽 'M6L15'、'KEY'，轴向尺寸 '35±1'、'131.2±0.5'、'3±0.3'，形位公差标注 '0.06 A'、'0.02 A'，基准符号 'A'，中心线标识 '85 MAX'。该图纸仅展示连接器、端子、插头的物理安装位置与外形结构，未包含针脚编号、引脚功能、线色或接线表等 pinout 信息，完全符合 mechanical_dimensions 类别的判定标准。",
        "confidence": 0.95,
        "source": "ai",
        "category_type": "base"
      }
    },
    {
      "region_id": "R002",
      "group_name": "R002",
      "origin_src": "regions/R002_ffd700.png",
      "target_src": "regions/R002_ffd700_trimmed.png",
      "content_type": "structure",
      "is_structure": true,
      "has_gb_standard": false,
      "title": {
        "title_zh": "电机线缆出线结构",
        "title_en": "Motor Cable Exit Structure"
      },
      "classification": {
        "category_name": "mechanical_dimensions",
        "title_zh": "机械结构尺寸",
        "title_en": "Mechanical Dimensions",
        "category_basis": "用于识别机械结构尺寸类图纸，包括电机/零部件外形轮廓、长宽高、轴径、轴长、键槽、法兰、安装孔、孔距、定位尺寸、三视图、剖视图、局部放大视图、公差、形位公差、基准符号、连接器/线缆/插头的物理安装位置或外形位置。若图中仅展示连接器型号、端子型号、线束走向、接口外形位置，但没有明确的引脚编号、针脚功能、线色或接线表，也归入本类。",
        "reason": "该图展示了电机端部三根线缆(Brake Wire、Power Wire、Feedback Wire)的物理出线结构和走向，以及连接器SM-6P的安装位置、安装孔尺寸(4-Ø6.5)、法兰外形尺寸(□80)、角度标注(45°、Ø90)和线缆长度公差(200+50/0)。图中仅标注了线缆名称、长度、连接器型号和物理安装位置，未体现引脚编号、针脚功能、线色或接线表，符合mechanical_dimensions分类标准中'连接器/线缆/插头的物理安装位置或外形位置'的定义。",
        "confidence": 0.95,
        "source": "ai",
        "category_type": "base"
      }
    },
    {
      "region_id": "R003",
      "group_name": "R003_KEY_dimensions",
      "origin_src": "regions/R003_00bfff.png",
      "target_src": "regions/R003_00bfff_trimmed.png",
      "content_type": "structure",
      "is_structure": true,
      "has_gb_standard": false,
      "title": {
        "title_zh": "键槽尺寸",
        "title_en": "Key Dimensions"
      },
      "classification": {
        "category_name": "mechanical_dimensions",
        "title_zh": "机械尺寸",
        "title_en": "Mechanical Dimensions",
        "category_basis": "用于识别机械结构尺寸类图纸，包括电机/零部件外形轮廓、长宽高、轴径、轴长、键槽、法兰、安装孔、孔距、定位尺寸、三视图、剖视图、局部放大视图、公差、形位公差、基准符号、连接器/线缆/插头的物理安装位置或外形位置。若图中仅展示连接器型号、端子型号、线束走向、接口外形位置，但没有明确的引脚编号、针脚功能、线色或接线表，也归入本类。",
        "reason": "目标图像显示键槽的机械尺寸视图，包含左侧视图和右侧视图，标注了键槽长度25、键槽宽度6等关键尺寸参数，底部标注'KEY'说明这是键槽结构，完全符合机械尺寸类图纸的特征",
        "confidence": 0.98,
        "source": "ai",
        "category_type": "base"
      }
    },
    {
      "region_id": "R004",
      "group_name": "power_wire_pinout_table",
      "origin_src": "regions/R004_8a2be2.png",
      "target_src": "",
      "content_type": "table",
      "is_structure": false,
      "has_gb_standard": false,
      "title": {
        "title_zh": "动力线接线定义表",
        "title_en": "Power Wire Pinout Table"
      },
      "classification": {
        "category_name": "power_connector_pinout",
        "title_zh": "动力连接器针脚定义",
        "title_en": "Power Connector Pinout",
        "category_basis": "用于识别动力连接器或电源接口的针脚/接线定义，包括动力接口 pinout、引脚编号与针脚功能对应关系、针脚名称、U/V/W/PE、L/N/PE、DC+/DC-、P+/P-、Brake+/Brake-、制动器、电源正负极、保护地、相线、线色、线径、端子号、接线说明、连接器针位图、针脚分配表。\n\n必须同时满足：\n1. 出现连接器针脚、端子或接口信息；\n2. 至少有一个针脚编号与功能、信号名、线色、线序、电源极性、相线、保护地或接线关系对应。\n\n仅有引脚编号，但没有功能定义，不应归入本类。\n仅出现 Power Wire、Housing、Terminal、连接器型号、端子型号、线束走向、连接器安装位置、接插件外形图、插头/插座物料信息时，不应归入本类。\n仅显示 1/2/3/4 等孔位编号和 Housing/Terminal 型号，应归入 connector_housing_terminal 或 connector_structure，不应归入 power_connector_pinout。",
        "reason": "该图为典型的动力连接器针脚定义表，明确列出了针脚编号1/2/3/4，对应相线U/V/W和保护地PE，以及各针脚的线色白WH/红RD/黑BK/黄绿YE/GN，并标注了线径13AWG。完全符合category_basis中要求的引脚编号与针脚功能、相线、保护地、线色对应关系。",
        "confidence": 0.98,
        "source": "ai",
        "category_type": "base"
      }
    },
    {
      "region_id": "R005",
      "group_name": "SP2111/P5_connector_pinout",
      "origin_src": "regions/R005_8a2be2.png",
      "target_src": "regions/R005_8a2be2_trimmed.png",
      "content_type": "structure",
      "is_structure": true,
      "has_gb_standard": false,
      "title": {
        "title_zh": "SP2111/P5 连接器针脚图",
        "title_en": "SP2111/P5 Connector Pinout"
      },
      "classification": {
        "category_name": "mechanical_dimensions",
        "title_zh": "机械尺寸",
        "title_en": "Mechanical Dimensions",
        "category_basis": "用于识别机械结构尺寸类图纸，包括电机/零部件外形轮廓、长宽高、轴径、轴长、键槽、法兰、安装孔、孔距、定位尺寸、三视图、剖视图、局部放大视图、公差、形位公差、基准符号、连接器/线缆/插头的物理安装位置或外形位置。若图中仅展示连接器型号、端子型号、线束走向、接口外形位置，但没有明确的引脚编号、针脚功能、线色或接线表，也归入本类。",
        "reason": "目标图像展示了 SP2111/P5 连接器的圆形插头外形结构，可见 5 个孔位的物理排布（编号 1、2、3、4、5）及外形轮廓，但未标注针脚功能、信号名称、线色或接线关系，仅显示孔位编号和连接器型号，符合机械尺寸类图纸中'连接器外形位置'的定义",
        "confidence": 0.92,
        "source": "ai",
        "category_type": "base"
      }
    },
    {
      "region_id": "R006",
      "group_name": "feedback_connector_pinout_table",
      "origin_src": "regions/R006_00ff7f.png",
      "target_src": "",
      "content_type": "table",
      "is_structure": false,
      "has_gb_standard": false,
      "title": {
        "title_zh": "反馈线接口定义",
        "title_en": "Feedback Connector Pinout"
      },
      "classification": {
        "category_name": "feedback_connector_pinout",
        "title_zh": "反馈连接器针脚定义",
        "title_en": "Feedback Connector Pinout",
        "category_basis": "用于识别编码器、反馈器、传感器或信号连接器的针脚/信号定义，包括反馈接口 pinout、17-pin/15-pin/9-pin/多芯信号接口、引脚编号、VCC、+5V、+12V、GND、0V、A+/A-/B+/B-/Z+/Z-、U/V/W Hall、Hall A/B/C、SIN/COS、S+/S-、CLK/DATA、SD+/SD-、FG、Shield、NC、信号脚、屏蔽线、线色、接线说明、针脚分配表。必须体现信号功能、针脚编号、线序、线色或反馈接口定义；仅出现连接器外形、Housing、Terminal、线束走向或安装位置时，不应归入本类。",
        "reason": "该图表明确标注了 'Feedback' 反馈线接口的针脚定义表，包含引脚编号 1-6、信号功能（DC +5V、GND、VB+、VB-、SD+、SD-）、线色标识（红 RD、黑 BK、棕 BN、白 WH、蓝 BU、黄 YE）以及线径规格 28AWG，完全符合反馈连接器 pinout 的典型特征，体现了编码器或传感器接口的针脚分配和接线说明。",
        "confidence": 0.98,
        "source": "ai",
        "category_type": "base"
      }
    },
    {
      "region_id": "R007",
      "group_name": "SC-06_connector_pinout",
      "origin_src": "regions/R007_00ff7f.png",
      "target_src": "regions/R007_00ff7f_trimmed.png",
      "content_type": "structure",
      "is_structure": true,
      "has_gb_standard": false,
      "title": {
        "title_zh": "SC-06 连接器针脚定义",
        "title_en": "SC-06 Connector Pinout"
      },
      "classification": {
        "category_name": "feedback_connector_pinout",
        "title_zh": "反馈连接器针脚定义",
        "title_en": "Feedback Connector Pinout",
        "category_basis": "用于识别编码器、反馈器、传感器或信号连接器的针脚/信号定义，包括反馈接口 pinout、17-pin/15-pin/9-pin/多芯信号接口、引脚编号、VCC、+5V、+12V、GND、0V、A+/A-/B+/B-/Z+/Z-、U/V/W Hall、Hall A/B/C、SIN/COS、S+/S-、CLK/DATA、SD+/SD-、FG、Shield、NC、信号脚、屏蔽线、线色、接线说明、针脚分配表。必须体现信号功能、针脚编号、线序、线色或反馈接口定义；仅出现连接器外形、Housing、Terminal、线束走向或安装位置时，不应归入本类。",
        "reason": "目标裁剪图显示 SC-06 连接器的六针脚编号布局（针脚 1-6），结合完整标记图中左侧表格，SC-06 对应 'Feedback' 反馈接口，表格明确列出 VCC、GND、A+、A-、B+、B- 等反馈信号功能与针脚对应关系，符合编码器/反馈器针脚定义特征。",
        "confidence": 0.95,
        "source": "ai",
        "category_type": "base"
      }
    },
    {
      "region_id": "R008",
      "group_name": "tolerance_table",
      "origin_src": "regions/R008_ff8c00.png",
      "target_src": "",
      "content_type": "table",
      "is_structure": false,
      "has_gb_standard": false,
      "title": {
        "title_zh": "未注线性公差表",
        "title_en": "Undeclared Linear Tolerance Table"
      },
      "classification": {
        "category_name": "mechanical_dimensions",
        "title_zh": "机械尺寸",
        "title_en": "Mechanical Dimensions",
        "category_basis": "用于识别机械结构尺寸类图纸，包括电机/零部件外形轮廓、长宽高、轴径、轴长、键槽、法兰、安装孔、孔距、定位尺寸、三视图、剖视图、局部放大视图、公差、形位公差、基准符号、连接器/线缆/插头的物理安装位置或外形位置。若图中仅展示连接器型号、端子型号、线束走向、接口外形位置，但没有明确的引脚编号、针脚功能、线色或接线表，也归入本类。",
        "reason": "该图为未注线性公差表，明确列出了不同尺寸范围的公差值，属于机械制图中的公差标注规范，符合 'mechanical_dimensions' 类别中的'公差'定义。图像中可见尺寸区间 '0.5~3'、'>3~6'、'>6~30'、'>30~120'、'>120~400' 及对应的公差值 '±0.2'、'±0.3'、'±0.5'、'±0.8'、'±1.2'，属于机械结构尺寸类图纸的标准公差规定。",
        "confidence": 0.95,
        "source": "ai",
        "category_type": "base"
      }
    },
    {
      "region_id": "R009",
      "group_name": "connector_housing_terminal_2",
      "origin_src": "regions/R009_1e90ff.png",
      "target_src": "",
      "content_type": "text",
      "is_structure": false,
      "has_gb_standard": false,
      "title": {
        "title_zh": "2针连接器壳体与端子型号",
        "title_en": "2-Pin Connector Housing and Terminal Model"
      },
      "classification": {
        "category_name": "mechanical_dimensions",
        "title_zh": "机械结构尺寸",
        "title_en": "Mechanical Dimensions",
        "category_basis": "用于识别机械结构尺寸类图纸，包括电机/零部件外形轮廓、长宽高、轴径、轴长、键槽、法兰、安装孔、孔距、定位尺寸、三视图、剖视图、局部放大视图、公差、形位公差、基准符号、连接器/线缆/插头的物理安装位置或外形位置。若图中仅展示连接器型号、端子型号、线束走向、接口外形位置，但没有明确的引脚编号、针脚功能、线色或接线表，也归入本类。",
        "reason": "目标图像显示2针连接器的示意图，包含编号'2'、'1'的孔位图示，以及Housing型号'H66L6-02P'和Terminal型号'T66L6-B'。图中仅展示连接器外形结构、孔位编号和物料型号信息，未包含针脚功能定义、信号名称、线色、电源极性或接线关系等电气连接信息，符合mechanical_dimensions类别中'仅展示连接器型号、端子型号、接口外形位置'的定义。",
        "confidence": 0.95,
        "source": "ai",
        "category_type": "base"
      }
    },
    {
      "region_id": "R010",
      "group_name": "brake_wire_pinout",
      "origin_src": "regions/R010_1e90ff.png",
      "target_src": "",
      "content_type": "table",
      "is_structure": false,
      "has_gb_standard": false,
      "title": {
        "title_zh": "刹车线接线定义",
        "title_en": "Brake Wire Connection Definition"
      },
      "classification": {
        "category_name": "power_connector_pinout",
        "title_zh": "动力连接器针脚定义",
        "title_en": "Power Connector Pinout",
        "category_basis": "用于识别动力连接器或电源接口的针脚/接线定义，包括动力接口 pinout、引脚编号与针脚功能对应关系、针脚名称、U/V/W/PE、L/N/PE、DC+/DC-、P+/P-、Brake+/Brake-、制动器、电源正负极、保护地、相线、线色、线径、端子号、接线说明、连接器针位图、针脚分配表。\n\n必须同时满足：\n1. 出现连接器针脚、端子或接口信息；\n2. 至少有一个针脚编号与功能、信号名、线色、线序、电源极性、相线、保护地或接线关系对应。\n\n仅有引脚编号，但没有功能定义，不应归入本类。\n仅出现 Power Wire、Housing、Terminal、连接器型号、端子型号、线束走向、连接器安装位置、接插件外形图、插头/插座物料信息时，不应归入本类。\n仅显示 1/2/3/4 等孔位编号和 Housing/Terminal 型号，应归入 connector_housing_terminal 或 connector_structure，不应归入 power_connector_pinout。",
        "reason": "图中显示了刹车线 Brake 接口的针脚编号 1、2，对应功能为刹车BK(+)和刹车BK(-)，明确标注了线色红 RD 和兰 BU，以及线径 18AWG。满足动力连接器 pinout 定义的典型特征：针脚编号、功能名称 Brake+/-、线色、线径，符合制动器接线定义场景。",
        "confidence": 0.95,
        "source": "ai",
        "category_type": "base"
      }
    },
    {
      "region_id": "R011",
      "group_name": "R011",
      "origin_src": "regions/R011_adff2f.png",
      "target_src": "regions/R011_adff2f_trimmed.png",
      "content_type": "structure",
      "is_structure": true,
      "has_gb_standard": false,
      "title": {
        "title_zh": "TN曲线图",
        "title_en": "TN Graph"
      },
      "classification": {
        "category_name": "torque_speed_curve",
        "title_zh": "扭矩-转速曲线",
        "title_en": "Torque-Speed Curve",
        "category_basis": "用于识别电机性能曲线类图纸或图表，包括扭矩-转速曲线、转速-扭矩关系、连续扭矩、峰值扭矩、间歇扭矩、额定扭矩、最大扭矩、转速范围、额定转速、最高转速、工作区间、S1/S2/S3 工作制、短时运行区、连续运行区、功率曲线、效率曲线等。典型特征是坐标轴、曲线、工作区域、转速单位 rpm/r/min、扭矩单位 Nm/N·m。",
        "reason": "图纸显示典型的扭矩-转速性能曲线图，纵轴为转矩(N·m)，横轴为转速(rpm)，曲线标注了关键点(9.54,2200)和(3.18,3000)，并划分了短时工作区和连续工作区，完全符合电机性能曲线类图纸的典型特征。",
        "confidence": 0.98,
        "source": "ai",
        "category_type": "base"
      }
    },
    {
      "region_id": "R012",
      "group_name": "电机性能参数",
      "origin_src": "regions/R012_40e0d0.png",
      "target_src": "",
      "content_type": "table",
      "is_structure": false,
      "has_gb_standard": false,
      "title": {
        "title_zh": "电机性能参数表",
        "title_en": "Motor Performance Parameters"
      },
      "classification": {
        "category_name": "torque_speed_curve",
        "title_zh": "扭矩-转速曲线",
        "title_en": "Torque-Speed Curve",
        "category_basis": "用于识别电机性能曲线类图纸或图表，包括扭矩-转速曲线、转速-扭矩关系、连续扭矩、峰值扭矩、间歇扭矩、额定扭矩、最大扭矩、转速范围、额定转速、最高转速、工作区间、S1/S2/S3 工作制、短时运行区、连续运行区、功率曲线、效率曲线等。典型特征是坐标轴、曲线、工作区域、转速单位 rpm/r/min、扭矩单位 Nm/N·m。",
        "reason": "该表格完整列举了电机的额定扭矩 3.18 N·m、最大扭矩 9.54 N·m、额定转速 3000 rpm、最大转速 3500 rpm、额定功率 1000 W、连续静态扭矩 3.5 N·m、转矩常数 0.149 N·m/A 等核心性能参数，体现了扭矩与转速的关系和电机运行范围，虽无曲线图但在结构上与性能图表密切关联，属于扭矩-转速性能参数数据表。",
        "confidence": 0.88,
        "source": "ai",
        "category_type": "base"
      }
    },
    {
      "region_id": "R013",
      "group_name": "制动器性能参数",
      "origin_src": "regions/R013_6495ed.png",
      "target_src": "",
      "content_type": "table",
      "is_structure": false,
      "has_gb_standard": false,
      "title": {
        "title_zh": "制动器性能参数",
        "title_en": "Brake performance parameters"
      },
      "classification": {
        "category_name": "mechanical_dimensions",
        "title_zh": "机械尺寸",
        "title_en": "Mechanical Dimensions",
        "category_basis": "用于识别机械结构尺寸类图纸，包括电机/零部件外形轮廓、长宽高、轴径、轴长、键槽、法兰、安装孔、孔距、定位尺寸、三视图、剖视图、局部放大视图、公差、形位公差、基准符号、连接器/线缆/插头的物理安装位置或外形位置。若图中仅展示连接器型号、端子型号、线束走向、接口外形位置，但没有明确的引脚编号、针脚功能、线色或接线表，也归入本类。",
        "reason": "该图为制动器性能参数表格，包含额定电压、静力矩、制动时间、释放时间、吸合电压等制动器规格参数。虽然不是典型的机械尺寸图纸，但作为零部件（制动器）的技术规格参数表，属于机械零部件相关的性能参数文档。由于现有分类中没有专门的'电气参数表'或'制动器参数'类别，而该表格描述的是制动器这一机械部件的性能特性，与机械零部件的技术规格密切相关，因此归入mechanical_dimensions是现有分类中最接近的选择。",
        "confidence": 0.65,
        "source": "ai",
        "category_type": "base"
      }
    },
    {
      "region_id": "R014",
      "group_name": "encoder_performance_parameters",
      "origin_src": "regions/R014_ffb347.png",
      "target_src": "",
      "content_type": "table",
      "is_structure": false,
      "has_gb_standard": false,
      "title": {
        "title_zh": "编码器性能参数",
        "title_en": "Encoder Performance Parameters"
      },
      "classification": {
        "category_name": "feedback_connector_pinout",
        "title_zh": "反馈连接器针脚定义",
        "title_en": "Feedback Connector Pinout",
        "category_basis": "用于识别编码器、反馈器、传感器或信号连接器的针脚/信号定义，包括反馈接口 pinout、17-pin/15-pin/9-pin/多芯信号接口、引脚编号、VCC、+5V、+12V、GND、0V、A+/A-/B+/B-/Z+/Z-、U/V/W Hall、Hall A/B/C、SIN/COS、S+/S-、CLK/DATA、SD+/SD-、FG、Shield、NC、信号脚、屏蔽线、线色、接线说明、针脚分配表。必须体现信号功能、针脚编号、线序、线色或反馈接口定义；仅出现连接器外形、Housing、Terminal、线束走向或安装位置时，不应归入本类。",
        "reason": "目标图像展示编码器性能参数表，包含编码器类型'绝对值式多圈磁编'和分辨率'131072(17bit)'、'65536(16bit)'，属于反馈器件的核心技术参数，用于定义编码器的信号精度和类型特征，符合反馈连接器相关技术规格定义范畴",
        "confidence": 0.75,
        "source": "ai",
        "category_type": "base"
      }
    }
  ],
  "quality_control": {
    "origin_src_is_pre_trim_crop": true,
    "target_src_is_structure_trimmed_crop": true,
    "engineering_extraction_skipped": true,
    "forbidden_engineering_fields_present": [],
    "json_validated": true,
    "origin_src_semantics": "5x crop before structure border trim; backend original data image",
    "target_src_semantics": "structure-only crop after border trim; backend processed data image"
  }
}