{
  "items": [
    {
      "id": "g0_i0_html",
      "kind": "table",
      "group_index": 0,
      "item_index": 0,
      "html": "<table><tr><th>角号 PIN</th><th>定义 FUNCTION</th><th>颜色 COLOR</th></tr><tr><td>1</td><td>U相 MOTOR U</td><td>黄 YELLOW</td></tr><tr><td>2</td><td>V相 MOTOR V</td><td>红 RED</td></tr><tr><td>3</td><td>W相 MOTOR W</td><td>黑 BLACK</td></tr><tr><td>4</td><td>PE相 MOTOR PE≐</td><td>黄绿 YELLOW/GREEN</td></tr></table>",
      "translation": "<table><tr><th>PIN</th><th>FUNCTION</th><th>COLOR</th></tr><tr><td>1</td><td>MOTOR U</td><td>YELLOW</td></tr><tr><td>2</td><td>MOTOR V</td><td>RED</td></tr><tr><td>3</td><td>MOTOR W</td><td>BLACK</td></tr><tr><td>4</td><td>MOTOR PE≐</td><td>YELLOW/GREEN</td></tr></table>"
    },
    {
      "id": "g2_i0_html",
      "kind": "table",
      "group_index": 2,
      "item_index": 0,
      "html": "<table><tr><th>角号 PIN</th><th>定义 FUNCTION</th><th>颜色 COLOR</th></tr><tr><td>1</td><td>VCC +5V</td><td>红 RED</td></tr><tr><td>2</td><td>GND</td><td>黑 BLACK</td></tr><tr><td>3</td><td>VB</td><td>棕 BROWN</td></tr><tr><td>4</td><td>电池GND</td><td>白 WHITE</td></tr><tr><td>5</td><td>485+</td><td>蓝 BLUE</td></tr><tr><td>6</td><td>485-</td><td>黄 YELLOW</td></tr></table>",
      "translation": "<table><tr><th>PIN</th><th>FUNCTION</th><th>COLOR</th></tr><tr><td>1</td><td>VCC +5V</td><td>RED</td></tr><tr><td>2</td><td>GND</td><td>BLACK</td></tr><tr><td>3</td><td>VB</td><td>BROWN</td></tr><tr><td>4</td><td>Battery GND</td><td>WHITE</td></tr><tr><td>5</td><td>485+</td><td>BLUE</td></tr><tr><td>6</td><td>485-</td><td>YELLOW</td></tr></table>"
    },
    {
      "id": "g6_i0_html",
      "kind": "table",
      "group_index": 6,
      "item_index": 0,
      "html": "<table><tr><td>技术参数</td><td></td></tr><tr><td>极数</td><td>10</td></tr><tr><td>直流母线电压 Uc(V)</td><td>300</td></tr><tr><td>额定功率 Pn(W)</td><td>750</td></tr><tr><td>额定转矩 Tn(N.m)</td><td>2.39</td></tr><tr><td>额定转速 nn(rpm)</td><td>3000</td></tr><tr><td>额定电流 In(A)</td><td>4</td></tr><tr><td>最大电流 Im(A)</td><td>12.6</td></tr><tr><td>最大转矩 Tm(N.m)</td><td>7.17</td></tr><tr><td>连续静态转矩 Ts(N.m)</td><td>2.63</td></tr><tr><td>连续静态电流 In(A)</td><td>4.4</td></tr><tr><td>线电阻 Resistance line-line RL(Ω)</td><td>1.75</td></tr><tr><td>线电感 Inductance line-line LL(mH)</td><td>8.1</td></tr><tr><td>电气时间常数 T e(ms)</td><td>4.63</td></tr><tr><td>机械时间常数 T m(ms)</td><td>0.711</td></tr><tr><td>反电势常数 Ke(V/krpm)</td><td>40</td></tr><tr><td>转矩常数 Kt(Nm/A)</td><td>0.662</td></tr><tr><td>转动惯量 Jm(Kg.cm²)</td><td>1.027</td></tr><tr><td>最大径向力 Fr(N)</td><td>335</td></tr><tr><td>最大轴向力 Fa(N)</td><td>167.5</td></tr><tr><td>反馈装置</td><td>锐鹰SROA46-M16S23Bit-SY-5V</td></tr><tr><td>绝缘等级</td><td>F</td></tr><tr><td>防护等级</td><td>IP65</td></tr><tr><td>重量(Kg)</td><td>2.3</td></tr></table>",
      "translation": ""
    }
  ]
}